subfix/__init__.py
subfix/log.py
subfix/subfix.py
tests/__init__.py
subfix-1.1.2.dist-info/LICENSE-APACHE
subfix-1.1.2.dist-info/LICENSE-MIT
subfix-1.1.2.dist-info/METADATA
subfix-1.1.2.dist-info/WHEEL
subfix-1.1.2.dist-info/entry_points.txt
subfix-1.1.2.dist-info/top_level.txt
subfix-1.1.2.dist-info/RECORD
