Metadata-Version: 2.1
Name: subfix
Version: 1.1.2
Summary: Subtitle fixer
Home-page: https://github.com/alin23/subfix
Author: Alin Panaitiu
Author-email: alin.p32@gmail.com
Maintainer: Alin Panaitiu
Maintainer-email: alin.p32@gmail.com
License: MIT/Apache-2.0
Platform: UNKNOWN
Classifier: Development Status :: 4 - Beta
Classifier: Intended Audience :: Developers
Classifier: License :: OSI Approved :: MIT License
Classifier: License :: OSI Approved :: Apache Software License
Classifier: Natural Language :: English
Classifier: Operating System :: OS Independent
Classifier: Programming Language :: Python :: 2.7
Classifier: Programming Language :: Python :: 3.5
Classifier: Programming Language :: Python :: 3.6
Classifier: Programming Language :: Python :: Implementation :: CPython
Classifier: Programming Language :: Python :: Implementation :: PyPy
Requires-Dist: fire
Requires-Dist: pysrt
Requires-Dist: daiquiri
